Makefile
bits_mod.py
setup.py
test-bits_mod
this-pylint
bits_mod.egg-info/PKG-INFO
bits_mod.egg-info/SOURCES.txt
bits_mod.egg-info/dependency_links.txt
bits_mod.egg-info/top_level.txt