Metadata-Version: 1.1
Name: bits-mod
Version: 1.00
Summary: Pure Python efficient array of bits
Home-page: http://stromberg.dnsalias.org/~strombrg/bits_mod/
Author: Daniel Richard Stromberg
Author-email: strombrg@gmail.com
License: Apache v2
Keywords: Bit Array List
Platform: Cross platform
Classifier: Development Status :: 5 - Production/Stable
Classifier: Intended Audience :: Developers
Classifier: Programming Language :: Python :: 2
Classifier: Programming Language :: Python :: 3
